[
    {
      "id": "615f6cdc9539afc0ee16fa63",
      "index": 0,
      "guid": "a8565b8f-93e7-4162-9010-234fd1150fbc",
      "isActive": false,
      "balance": "111,466.64",
      "picture": "http://placehold.it/32x32",
      "age": 21,
      "firstName": "Mccarty",
      "surName": "Juarez",
      "gender": "male",
      "company": "ZAPPIX",
      "email": "mccartyjuarez@zappix.com",
      "phone": "+1 (831) 428-3837",
      "status": 3,
      "address": "265 Village Road, Brethren, Rhode Island, 204",
      "about": "Irure ipsum voluptate enim dolor id qui anim mollit anim. Consequat sit dolore aute deserunt sit pariatur non anim culpa aliqua elit culpa ipsum cupidatat. Consequat dolore ea reprehenderit ex exercitation aute. Minim exercitation adipisicing fugiat aliquip nulla. Consectetur dolor amet pariatur consectetur eu duis exercitation id. Laboris irure tempor non exercitation dolor sunt velit cillum eiusmod. Mollit do nulla tempor velit tempor est.\r\n",
      "registered": "2015-01-02T10:15:28 -01:00",
      "friends": [
        {
          "id": 0,
          "name": "Reilly Sheppard"
        },
        {
          "id": 1,
          "name": "Keisha Arnold"
        },
        {
          "id": 2,
          "name": "Bridges Kerr"
        }
      ]
    },
    {
      "id": "615f6cdcbb5e95d06955aeb4",
      "index": 1,
      "guid": "4360d286-25cf-4cc8-895c-1faeea4f635e",
      "isActive": false,
      "balance": "283,080.19",
      "picture": "http://placehold.it/32x32",
      "age": 27,
      "firstName": "Mcneil",
      "surName": "Mills",
      "gender": "male",
      "company": "MITROC",
      "email": "mcneilmills@mitroc.com",
      "phone": "+1 (845) 494-3719",
      "status": 3,
      "address": "249 Dekoven Court, Stouchsburg, Wyoming, 1878",
      "about": "Amet fugiat ullamco do qui pariatur et cillum laboris adipisicing. Enim non nisi laborum non officia Lorem et. Et veniam incididunt eu enim. Dolore ad laborum aute ad. Sunt consequat non consectetur Lorem consectetur consectetur mollit est dolore mollit anim nisi incididunt. Laboris mollit sunt labore velit enim nisi consequat magna minim deserunt amet. Veniam eiusmod ullamco consequat consectetur esse sit proident do esse ipsum elit officia culpa.\r\n",
      "registered": "2016-07-02T09:43:03 -01:00",
      "friends": [
        {
          "id": 0,
          "name": "James Sparks"
        },
        {
          "id": 1,
          "name": "Ella Mcmahon"
        },
        {
          "id": 2,
          "name": "Lucas Vazquez"
        }
      ]
    },
    {
      "id": "615f6cdc50185c1c62131412",
      "index": 2,
      "guid": "6d803cd5-9d0b-4f9c-b526-924d04ff6269",
      "isActive": false,
      "balance": "196,631.07",
      "picture": "http://placehold.it/32x32",
      "age": 28,
      "firstName": "Deanna",
      "surName": "Snider",
      "gender": "female",
      "company": "TROPOLIS",
      "email": "deannasnider@tropolis.com",
      "phone": "+1 (920) 451-3263",
      "status": 3,
      "address": "594 Ridgewood Place, Norwood, Tennessee, 667",
      "about": "Voluptate consequat voluptate exercitation deserunt anim. Incididunt consequat adipisicing non do culpa quis eu velit nulla consequat magna occaecat. Ea amet adipisicing laboris ipsum irure esse adipisicing ex excepteur aliqua eu aliquip fugiat minim. In aute veniam sunt ipsum aliqua. Officia tempor est esse cillum velit elit voluptate eu. Sit magna ea aliqua culpa minim et.\r\n",
      "registered": "2019-07-27T10:37:32 -01:00",
      "friends": [
        {
          "id": 0,
          "name": "Rebekah Silva"
        },
        {
          "id": 1,
          "name": "Singleton Kirkland"
        },
        {
          "id": 2,
          "name": "Downs Santiago"
        }
      ]
    },
    {
      "id": "615f6cdc00a4683bd3b8cdce",
      "index": 3,
      "guid": "bd965241-557a-4a37-892c-e28172bea96e",
      "isActive": false,
      "balance": "124,418.11",
      "picture": "http://placehold.it/32x32",
      "age": 25,
      "firstName": "Desiree",
      "surName": "Hood",
      "gender": "female",
      "company": "QUOTEZART",
      "email": "desireehood@quotezart.com",
      "phone": "+1 (836) 487-2886",
      "status": 0,
      "address": "548 Montauk Court, Bradenville, Puerto Rico, 3039",
      "about": "Dolor cillum sunt nulla excepteur dolore qui esse. Do veniam aliqua id duis ex ut occaecat deserunt cillum ad consectetur proident id est. Labore sit anim proident cillum duis occaecat eu eiusmod tempor elit id ex. Et sit anim qui proident irure ut quis labore labore.\r\n",
      "registered": "2021-03-06T10:59:04 -01:00",
      "friends": [
        {
          "id": 0,
          "name": "Simmons Mckay"
        },
        {
          "id": 1,
          "name": "Gwen Orr"
        },
        {
          "id": 2,
          "name": "Curtis Merritt"
        }
      ]
    },
    {
      "id": "615f6cdc09bb85a55fd9ca4a",
      "index": 4,
      "guid": "df3a442c-0cca-4e7f-a6aa-bb4304d92b7b",
      "isActive": false,
      "balance": "177,308.84",
      "picture": "http://placehold.it/32x32",
      "age": 40,
      "firstName": "Solomon",
      "surName": "Middleton",
      "gender": "male",
      "company": "ANDERSHUN",
      "email": "solomonmiddleton@andershun.com",
      "phone": "+1 (997) 536-2568",
      "status": 0,
      "address": "232 Degraw Street, Chelsea, Iowa, 2924",
      "about": "Consectetur sit ea dolor consequat quis velit elit est occaecat reprehenderit aliquip Lorem est. Irure dolor pariatur excepteur voluptate excepteur nostrud consectetur magna culpa. Excepteur officia culpa sit esse non duis exercitation consequat. Enim qui culpa est amet magna veniam adipisicing dolor tempor consectetur ut voluptate mollit laboris.\r\n",
      "registered": "2014-12-22T09:35:46 -01:00",
      "friends": [
        {
          "id": 0,
          "name": "Donovan Knowles"
        },
        {
          "id": 1,
          "name": "Wendy Blevins"
        },
        {
          "id": 2,
          "name": "Whitley Dejesus"
        }
      ]
    },
    {
      "id": "615f6cdc8e727088859ee408",
      "index": 5,
      "guid": "e44d9618-241c-4c1d-8a7e-c700ed4c9cb1",
      "isActive": true,
      "balance": "396,341.59",
      "picture": "http://placehold.it/32x32",
      "age": 24,
      "firstName": "Hart",
      "surName": "Taylor",
      "gender": "male",
      "company": "DIGIQUE",
      "email": "harttaylor@digique.com",
      "phone": "+1 (934) 595-3782",
      "status": 0,
      "address": "532 Herzl Street, Welch, Alabama, 2824",
      "about": "In elit aliqua officia fugiat laboris officia consectetur sit est minim ipsum. Consectetur commodo incididunt ad excepteur do sit esse commodo nostrud commodo ullamco veniam esse. Do sint incididunt esse ad cupidatat ea aute. Duis elit qui consectetur nisi adipisicing amet proident. Eiusmod duis voluptate aliqua labore in dolore quis ea qui. Eiusmod cupidatat nisi consequat culpa amet tempor labore culpa consequat dolor eiusmod amet. Minim amet et consectetur culpa occaecat consequat qui ex nostrud enim.\r\n",
      "registered": "2021-06-06T11:42:08 -01:00",
      "friends": [
        {
          "id": 0,
          "name": "Carver Kelly"
        },
        {
          "id": 1,
          "name": "Esperanza Hickman"
        },
        {
          "id": 2,
          "name": "Velazquez Fulton"
        }
      ]
    },
    {
      "id": "615f6cdca8d502578e69b2d3",
      "index": 6,
      "guid": "43df013a-cfe8-474b-a366-c46b35ae1397",
      "isActive": true,
      "balance": "359,843.84",
      "picture": "http://placehold.it/32x32",
      "age": 35,
      "firstName": "Mccoy",
      "surName": "Jefferson",
      "gender": "male",
      "company": "NSPIRE",
      "email": "mccoyjefferson@nspire.com",
      "phone": "+1 (880) 521-2575",
      "status": 0,
      "address": "698 Agate Court, Manitou, Nebraska, 5291",
      "about": "Id ad ea fugiat in exercitation minim culpa fugiat esse culpa do. Sit aute voluptate laborum mollit enim anim elit cupidatat consequat aliquip duis. Laborum aliqua minim dolore aute adipisicing. Non duis ut sit do ex consectetur commodo. Mollit Lorem aliqua reprehenderit laborum in dolor anim eu in reprehenderit. Duis proident tempor magna dolore pariatur et.\r\n",
      "registered": "2021-09-30T11:50:46 -01:00",
      "friends": [
        {
          "id": 0,
          "name": "Estes Peters"
        },
        {
          "id": 1,
          "name": "Witt Goodman"
        },
        {
          "id": 2,
          "name": "Beryl Leblanc"
        }
      ]
    },
    {
      "id": "615f6cdcc80108dcd6cba304",
      "index": 7,
      "guid": "7765c44d-c8d2-46c1-b9b2-440cf49e9a26",
      "isActive": false,
      "balance": "148,978.60",
      "picture": "http://placehold.it/32x32",
      "age": 35,
      "firstName": "Payne",
      "surName": "Fisher",
      "gender": "male",
      "company": "ZAGGLES",
      "email": "paynefisher@zaggles.com",
      "phone": "+1 (842) 500-2982",
      "status": 3,
      "address": "257 Pierrepont Street, Wildwood, Massachusetts, 2383",
      "about": "Officia proident aliquip ullamco qui irure incididunt dolore enim officia quis ex duis irure tempor. Cupidatat pariatur sunt excepteur reprehenderit sint non est proident officia amet voluptate dolore. Laborum Lorem incididunt id id qui laborum. Eiusmod aliquip cillum do et mollit veniam ut dolore nostrud aliquip nulla ullamco. Anim minim ullamco sunt labore sint irure consequat magna. Irure laborum ea ut esse in anim velit ipsum. Laboris reprehenderit anim irure ea aliqua tempor adipisicing aliqua irure aliquip culpa laborum ad culpa.\r\n",
      "registered": "2021-08-03T07:39:28 -01:00",
      "friends": [
        {
          "id": 0,
          "name": "Patton Gomez"
        },
        {
          "id": 1,
          "name": "Ross Kaufman"
        },
        {
          "id": 2,
          "name": "Mathews Fernandez"
        }
      ]
    }
  ]